fichier/cli.py
fichier/structure.py
fichier/tmp.py
fichier-0.1.0.dist-info/METADATA
fichier-0.1.0.dist-info/WHEEL
fichier-0.1.0.dist-info/entry_points.txt
fichier-0.1.0.dist-info/top_level.txt
fichier-0.1.0.dist-info/RECORD
