Metadata-Version: 2.4
Name: fichier
Version: 0.1.0
Summary: Outils pour fichiers, comme tree -a
Author-email: TonNom <ton.email@example.com>
Requires-Python: >=3.6
